{
    "867176767022301204": {
        "score": 0.5333333333333333,
        "ping_time": 0.5333333333333333,
        "penalties": 0,
        "acceptances": 1,
        "acceptance_time": 0.1,
        "acceptances_missed": 0,
        "no_reasons": 0,
        "reasons": 0,
        "votes_started": 0,
        "valid_votes": 0,
        "invalid_votes": 1,
        "voted_against": 0,
        "vote_penalties": 0
    },
    "221264723512000512": {
        "score": 90.41666666666667,
        "ping_time": 0.4166666666666667,
        "penalties": 30,
        "acceptances": 0,
        "acceptance_time": 0,
        "acceptances_missed": 0,
        "no_reasons": 0,
        "reasons": 1,
        "votes_started": 0,
        "valid_votes": 0,
        "invalid_votes": 0,
        "voted_against": 1,
        "vote_penalties": 60
    },
    "312250768038297600": {
        "score": 0,
        "ping_time": 0,
        "penalties": 0,
        "acceptances": 0,
        "acceptance_time": 0,
        "acceptances_missed": 0,
        "no_reasons": 0,
        "reasons": 0,
        "votes_started": 1,
        "valid_votes": 0,
        "invalid_votes": 0,
        "voted_against": 0,
        "vote_penalties": 0
    }
}